setup.py
staticbs/__init__.py
staticbs/common.py
staticbs/eobjs.py
staticbs/iobjs.py
staticbs/shapes.py
staticbs.egg-info/PKG-INFO
staticbs.egg-info/SOURCES.txt
staticbs.egg-info/dependency_links.txt
staticbs.egg-info/not-zip-safe
staticbs.egg-info/requires.txt
staticbs.egg-info/top_level.txt