Metadata-Version: 1.1
Name: staticbs
Version: 0.1
Summary: A simple 3D electro-magnetostatic biot-savart solving simulator
Home-page: https://github.com/grungy/staticbs
Author: Josh Marks and Andrea Waite
Author-email: jmarks@udel.edu
License: MIT
Platform: UNKNOWN
Classifier: Development Status :: 5 - Production/Stable
Classifier: License :: OSI Approved :: MIT License
Classifier: Programming Language :: Python :: 2.7
Classifier: Intended Audience :: Science/Research
Classifier: Topic :: Scientific/Engineering :: Physics
Classifier: Topic :: Scientific/Engineering :: Visualization
